[
  {
    "content_id": 717229,
    "reference_id": 6886,
    "title": "Fineias",
    "media_type": "Text",
    "index_reference": "fineias",
    "language": "por",
    "content": "<h1>FINEIAS</h1><ol><li><p>O filho de Eleazar e neto de Arão (<a href=\"https://ref.ly/Exod6:25\">Êx 6.25</a>). Ele também foi o pai de Abisua (<a href=\"https://ref.ly/1Chr6:4,1Chr6:50\">1Cr 6.4,50</a>). Enquanto Eleazar servia como sumo sacerdote, Fineias estava encarregado dos porteiros do tabernáculo (<a href=\"https://ref.ly/1Chr9:20\">1Cr 9.20</a>). Eleazar, seu pai, era encarregado dos porteiros quando Arão era o sumo sacerdote (compare <a href=\"https://ref.ly/Num3:32\">Nm 3.32</a>).</p><p>Quando os israelitas pecaram adorando Baal de Peor em Sitim, Fineias ficou muito irritado. Ele matou tanto um homem israelita quanto uma mulher midianita por causa de seu comportamento imoral (<a href=\"https://ref.ly/Num25:7\">Nm 25.7</a>). Após essa ação, Deus não estava mais irado com Israel. Deus fez um acordo especial (aliança) de paz com Fineias, prometendo que ele e seus descendentes sempre serviriam como sacerdotes (<a href=\"https://ref.ly/Num25:11-Num25:13\">Nm 25.11–13</a>). Este feito foi contado como justiça para Fineias por todas as gerações futuras (<a href=\"https://ref.ly/Ps106:30\">Sl 106.30</a>). Exceto por um curto período, quando Eli serviu como sumo sacerdote (compare <a href=\"https://ref.ly/1Sam1:1-1Sam3:21\">1Sm 1–3</a>; <a href=\"https://ref.ly/1Sam14:3\">14.3</a>), Fineias e seus descendentes serviram como sumos sacerdotes até que os romanos destruíram o templo de Jerusalém em 70 d.C.</p><p>Após o incidente com Baal de Peor, Fineias juntou-se a Israel na luta contra os midianitas (<a href=\"https://ref.ly/Num31:6\">Nm 31.6</a>). Depois que Israel tomou o controle da terra de Canaã, Fineias recebeu a cidade de Gibeá na região montanhosa de Efraim como sua herança (<a href=\"https://ref.ly/Josh24:33\">Js 24.33</a>). Mais tarde, ele foi enviado com alguns líderes israelitas para questionar sobre um altar que foi construído no lado oeste do rio Jordão pelas tribos israelitas que viviam no lado leste (<a href=\"https://ref.ly/Josh22:13,Josh22:30-Josh22:32\">Js 22.13,30–32</a>). Em outra ocasião, em Betel, Fineias prometeu a Israel vitória na batalha contra a tribo de Benjamim (<a href=\"https://ref.ly/Judg20:28\">Jz 20.28</a>). Seus descendentes, Esdras, o escriba, e Gérson, retornaram com suas famílias a Jerusalém após o exílio na Babilônia (<a href=\"https://ref.ly/Ezra7:5\">Ed 7.5</a>;<a href=\"https://ref.ly/Ezra8:2\">8.2</a>).</p></li><li><p>Um dos dois filhos de Eli, que serviu como sacerdote em Siló (<a href=\"https://ref.ly/1Sam1:3\">1Sm 1.3</a>). De acordo com 1 Samuel, este Fineias era um sacerdote terrível. Ele e seu irmão Hofni abusaram dos sacrifícios que as pessoas ofereciam (<a href=\"https://ref.ly/1Sam2:12-1Sam2:17\">1Sm 2.12–17</a>). Eles desrespeitaram o santuário (<a href=\"https://ref.ly/1Sam2:22\">1Sm 2.22</a>). Eles ignoraram os avisos de seu pai Eli (<a href=\"https://ref.ly/1Sam2:25\">1Sm 2.25</a>). Um homem de Deus disse a Eli que seu filho morreria (<a href=\"https://ref.ly/1Sam2:34\">1Sm 2.34</a>). Mais tarde, durante uma guerra com os filisteus, Fineias foi morto no mesmo dia em que sua esposa deu à luz seu filho, que foi chamado de Icabô (<a href=\"https://ref.ly/1Sam4:11,1Sam4:17-1Sam4:19\">1Sm 4.11,17–19</a>; <a href=\"https://ref.ly/1Sam14:3\">14.3</a>).</p></li><li><p>O pai de Eleazar. Este Eleazar ajudou Meremote e os levitas chamados Jozabade e Noadia a contar os metais valiosos e recipientes do templo durante o período após o exílio na Babilônia (<a href=\"https://ref.ly/Ezra8:33\">Ed 8.33</a>).</p></li></ol>",
    "associations": {
      "passage": [
        {
          "start_ref": "02006025",
          "start_ref_usfm": "EXO 6:25",
          "end_ref": "02006025",
          "end_ref_usfm": "EXO 6:25"
        },
        {
          "start_ref": "04003032",
          "start_ref_usfm": "NUM 3:32",
          "end_ref": "04003032",
          "end_ref_usfm": "NUM 3:32"
        },
        {
          "start_ref": "04025007",
          "start_ref_usfm": "NUM 25:7",
          "end_ref": "04025007",
          "end_ref_usfm": "NUM 25:7"
        },
        {
          "start_ref": "04031006",
          "start_ref_usfm": "NUM 31:6",
          "end_ref": "04031006",
          "end_ref_usfm": "NUM 31:6"
        },
        {
          "start_ref": "06022013",
          "start_ref_usfm": "JOS 22:13",
          "end_ref": "06022013",
          "end_ref_usfm": "JOS 22:13"
        },
        {
          "start_ref": "06024033",
          "start_ref_usfm": "JOS 24:33",
          "end_ref": "06024033",
          "end_ref_usfm": "JOS 24:33"
        },
        {
          "start_ref": "07020028",
          "start_ref_usfm": "JDG 20:28",
          "end_ref": "07020028",
          "end_ref_usfm": "JDG 20:28"
        },
        {
          "start_ref": "09001003",
          "start_ref_usfm": "1SA 1:3",
          "end_ref": "09001003",
          "end_ref_usfm": "1SA 1:3"
        },
        {
          "start_ref": "09002022",
          "start_ref_usfm": "1SA 2:22",
          "end_ref": "09002022",
          "end_ref_usfm": "1SA 2:22"
        },
        {
          "start_ref": "09002025",
          "start_ref_usfm": "1SA 2:25",
          "end_ref": "09002025",
          "end_ref_usfm": "1SA 2:25"
        },
        {
          "start_ref": "09002034",
          "start_ref_usfm": "1SA 2:34",
          "end_ref": "09002034",
          "end_ref_usfm": "1SA 2:34"
        },
        {
          "start_ref": "09004011",
          "start_ref_usfm": "1SA 4:11",
          "end_ref": "09004011",
          "end_ref_usfm": "1SA 4:11"
        },
        {
          "start_ref": "09014003",
          "start_ref_usfm": "1SA 14:3",
          "end_ref": "09014003",
          "end_ref_usfm": "1SA 14:3"
        },
        {
          "start_ref": "13006004",
          "start_ref_usfm": "1CH 6:4",
          "end_ref": "13006004",
          "end_ref_usfm": "1CH 6:4"
        },
        {
          "start_ref": "13006050",
          "start_ref_usfm": "1CH 6:50",
          "end_ref": "13006050",
          "end_ref_usfm": "1CH 6:50"
        },
        {
          "start_ref": "13009020",
          "start_ref_usfm": "1CH 9:20",
          "end_ref": "13009020",
          "end_ref_usfm": "1CH 9:20"
        },
        {
          "start_ref": "15007005",
          "start_ref_usfm": "EZR 7:5",
          "end_ref": "15007005",
          "end_ref_usfm": "EZR 7:5"
        },
        {
          "start_ref": "15008002",
          "start_ref_usfm": "EZR 8:2",
          "end_ref": "15008002",
          "end_ref_usfm": "EZR 8:2"
        },
        {
          "start_ref": "15008033",
          "start_ref_usfm": "EZR 8:33",
          "end_ref": "15008033",
          "end_ref_usfm": "EZR 8:33"
        },
        {
          "start_ref": "19106030",
          "start_ref_usfm": "PSA 106:30",
          "end_ref": "19106030",
          "end_ref_usfm": "PSA 106:30"
        },
        {
          "start_ref": "09002012",
          "start_ref_usfm": "1SA 2:12",
          "end_ref": "09002017",
          "end_ref_usfm": "1SA 2:17"
        },
        {
          "start_ref": "04025011",
          "start_ref_usfm": "NUM 25:11",
          "end_ref": "04025013",
          "end_ref_usfm": "NUM 25:13"
        },
        {
          "start_ref": "09001001",
          "start_ref_usfm": "1SA 1:1",
          "end_ref": "09003021",
          "end_ref_usfm": "1SA 3:21"
        },
        {
          "start_ref": "06022030",
          "start_ref_usfm": "JOS 22:30",
          "end_ref": "06022032",
          "end_ref_usfm": "JOS 22:32"
        },
        {
          "start_ref": "09004017",
          "start_ref_usfm": "1SA 4:17",
          "end_ref": "09004019",
          "end_ref_usfm": "1SA 4:19"
        }
      ],
      "resource": []
    }
  }
]