[
  {
    "content_id": 811871,
    "reference_id": 7185,
    "title": "Réuma",
    "media_type": "Text",
    "index_reference": "réuma",
    "language": "fra",
    "content": "<h1>RÉUMA</h1><p>Concubine de Nachor (<a href=\"https://ref.ly/Gen22:24\">Gn 22.24</a>). Ses quatre fils sont devenus les ancêtres des tribus araméennes vivant au nord de Damas.</p>",
    "associations": {
      "passage": [
        {
          "start_ref": "01022024",
          "start_ref_usfm": "GEN 22:24",
          "end_ref": "01022024",
          "end_ref_usfm": "GEN 22:24"
        }
      ],
      "resource": []
    }
  }
]