[
  {
    "content_id": 648300,
    "reference_id": 2713,
    "title": "अमस्याह",
    "media_type": "Text",
    "index_reference": "अमस्याह",
    "language": "hin",
    "content": "<h1><span>अमस्याह</span></h1><p>यहोशापात के समय का एक सैन्य अगुवा, जो 200,000 पुरुषों का प्रभारी था। अमस्याह जिक्री का पुत्र था और बहुत ही भक्तिपूर्ण व्यक्ति था (<a href=\"https://ref.ly/2Chr17:16\">2&nbsp;इति 17:16</a>)। </p>",
    "associations": {
      "passage": [
        {
          "start_ref": "14017016",
          "start_ref_usfm": "2CH 17:16",
          "end_ref": "14017016",
          "end_ref_usfm": "2CH 17:16"
        }
      ],
      "resource": []
    }
  }
]