[
  {
    "content_id": 732807,
    "reference_id": 3750,
    "title": "क्लौदियुस का आदेश",
    "media_type": "Text",
    "index_reference": "क्लौदियुस का आदेश",
    "language": "hin",
    "content": "<h1>क्लौदियुस का आदेश</h1><p>नासरत में मिली एक संगमरमर की पटिया (पत्थर का एक सपाट टुकड़ा) पर खुदा हुआ एक संदेश है। यह संदेश लोगों को कब्रों से चोरी न करने की चेतावनी देता है। यह संभवतः तब लिखा गया था जब क्लौदियुस रोमी सम्राट थे, 41 और 54 ईस्वी के बीच। <em>देखें</em> <span data-bnType=\"resourceReference\" data-resourceId=\"5196\" data-resourceType=\"TyndaleBibleDictionary\">शिलालेख</span>।</p>",
    "associations": {
      "passage": [],
      "resource": [
        {
          "reference_id": 5196,
          "content_id": 381110,
          "resource_code": "TyndaleBibleDictionary",
          "label": "शिलालेख",
          "language": "hin"
        }
      ]
    }
  }
]