[
  {
    "content_id": 733353,
    "reference_id": 5807,
    "title": "कोइने यूनानी",
    "media_type": "Text",
    "index_reference": "कोइने यूनानी",
    "language": "hin",
    "content": "<h1>कोइने यूनानी </h1><p>यूनानी भाषा का एक रूप, जो रोमी साम्राज्य के समय के दौरान पश्चिम एशिया और भूमध्यसागरीय क्षेत्रों में व्यापक रूप से उपयोग किया जाता था। यूनानी में <em>कोइने</em> शब्द का अर्थ &quot;सामान्य&quot; होता है। यह वही यूनानी रूप था जिसका उपयोग नए नियम को लिखने और सेप्टुआजेंट (पुराने नियम का यूनानी अनुवाद) के लिए किया गया था।</p><p><em>देखें </em> <span data-bnType=\"resourceReference\" data-resourceId=\"3399\" data-resourceType=\"TyndaleBibleDictionary\">बाइबल</span>।</p>",
    "associations": {
      "passage": [],
      "resource": [
        {
          "reference_id": 3399,
          "content_id": 594429,
          "resource_code": "TyndaleBibleDictionary",
          "label": "बाइबल",
          "language": "hin"
        }
      ]
    }
  }
]