[
  {
    "content_id": 733058,
    "reference_id": 4602,
    "title": "गेशेम",
    "media_type": "Text",
    "index_reference": "गेशेम",
    "language": "hin",
    "content": "<h1>गेशेम</h1><p>नहेम्याह&nbsp;के एक अरबी विरोधी, जिसने यरूशलेम की शहरपनाह पुनर्निर्माण करने वालों का उपहास किया (<a href=\"https://ref.ly/Neh2:19\">नहे 2:19</a>; <a href=\"https://ref.ly/Neh6:1-Neh6:6\">6:1–6</a>)। यह संभव है कि वे उत्तरी अरब मरूभूमि में रहते थे। एक ददानी अरबी शिलालेख ने उन्हें &quot;गाश्मू,&quot; शाहर के पुत्र के रूप में पहचाना है। सम्बल्लत और तोबियाह की तरह, यरूशलेम का पुनर्निर्माण उनके आर्थिक हितों के लिए खतरा था।</p>",
    "associations": {
      "passage": [
        {
          "start_ref": "16002019",
          "start_ref_usfm": "NEH 2:19",
          "end_ref": "16002019",
          "end_ref_usfm": "NEH 2:19"
        },
        {
          "start_ref": "16006001",
          "start_ref_usfm": "NEH 6:1",
          "end_ref": "16006006",
          "end_ref_usfm": "NEH 6:6"
        }
      ],
      "resource": []
    }
  }
]