[
  {
    "content_id": 594443,
    "reference_id": 3541,
    "title": "गिद्ध",
    "media_type": "Text",
    "index_reference": "गिद्ध",
    "language": "hin",
    "content": "<h1>गिद्ध</h1><p>शिकार करने वाले पक्षियों में से कोई भी पक्षी जो अनुष्ठानिक रीति से अशुद्ध घोषित किए गए हैं (<a href=\"https://ref.ly/Deut14:13\">व्य.वि. 14:13</a>)। <em>देखें</em> <span data-bnType=\"resourceReference\" data-resourceId=\"3418\" data-resourceType=\"TyndaleBibleDictionary\">पक्षी</span>।</p>",
    "associations": {
      "passage": [
        {
          "start_ref": "05014013",
          "start_ref_usfm": "DEU 14:13",
          "end_ref": "05014013",
          "end_ref_usfm": "DEU 14:13"
        }
      ],
      "resource": [
        {
          "reference_id": 3418,
          "content_id": 381014,
          "resource_code": "TyndaleBibleDictionary",
          "label": "पक्षी",
          "language": "hin"
        },
        {
          "reference_id": 4398,
          "content_id": 594522,
          "resource_code": "Unknown",
          "label": "बाज",
          "language": "hin"
        },
        {
          "reference_id": 5797,
          "content_id": 594652,
          "resource_code": "Unknown",
          "label": "चील",
          "language": "hin"
        },
        {
          "reference_id": 8191,
          "content_id": 734089,
          "resource_code": "Unknown",
          "label": "गिद्ध",
          "language": "hin"
        }
      ]
    }
  }
]