[
  {
    "content_id": 649406,
    "reference_id": 6591,
    "title": "नोहा* (स्थान)",
    "media_type": "Text",
    "index_reference": "नोहा* (स्थान)",
    "language": "hin",
    "content": "<h1>नोहा* (स्थान)</h1><p>बिन्यामीन के क्षेत्र में से एक स्थान जो गिबा के पश्चिम में है (<a href=\"https://ref.ly/Judg20:43\">न्या 20:43</a>, आर.एस.वी.)। अन्य अनुवाद नोहा (जिसका अर्थ &quot;शांत&quot; है) को एक क्रिया विशेषण मानते हैं और इसे &quot;सहजता से&quot; (के.जे.वी.) के रूप में अनुवादित करते हैं, क्योंकि उस नाम का कोई नगर ज्ञात नहीं है।</p>",
    "associations": {
      "passage": [
        {
          "start_ref": "07020043",
          "start_ref_usfm": "JDG 20:43",
          "end_ref": "07020043",
          "end_ref_usfm": "JDG 20:43"
        }
      ],
      "resource": []
    }
  }
]