[
  {
    "content_id": 594448,
    "reference_id": 3593,
    "title": "लालड़ी",
    "media_type": "Text",
    "index_reference": "लालड़ी",
    "language": "hin",
    "content": "<h1>लालड़ी</h1><p>एक लाल या अग्निमय रंग की मणि, जैसे कि लालड़ी या माणिक्य। इसका उल्लेख महायाजक के चपरास में लगे मणि में से एक के रूप में किया गया है (<a href=\"https://ref.ly/Exod28:17\">निर्ग 28:17</a>)।</p><p><em>देखिए</em> <span data-bnType=\"resourceReference\" data-resourceId=\"7796\" data-resourceType=\"TyndaleBibleDictionary\">अनमोल मणि</span><span>।</span></p><p></p><p></p>",
    "associations": {
      "passage": [
        {
          "start_ref": "02028017",
          "start_ref_usfm": "EXO 28:17",
          "end_ref": "02028017",
          "end_ref_usfm": "EXO 28:17"
        }
      ],
      "resource": [
        {
          "reference_id": 7796,
          "content_id": 185016,
          "resource_code": "TyndaleBibleDictionary",
          "label": "बहुमूल्य पत्थर",
          "language": "hin"
        }
      ]
    }
  }
]