[
  {
    "content_id": 381516,
    "reference_id": 4797,
    "title": "हमोर",
    "media_type": "Text",
    "index_reference": "हमोर",
    "language": "hin",
    "content": "<h1>हमोर</h1><p>हमोर <span>शेकेम</span> के आसपास के क्षेत्र का हिब्बी या होरी राजकुमार था (<a href=\"https://ref.ly/Gen34:2\">उत 34:2</a>), जिससे याकूब ने भूमि खरीदी जब वे अपने परिवार के साथ पद्दनराम से लौट रहा था। इस समय हमोर के पुत्र शेकेम ने याकूब की पुत्री दीना के साथ व्यभिचार किया। अपने पुत्र के आग्रह पर हमोर ने याकूब से शेकेम और दीना के बीच विवाह सम्बन्ध के लिए प्रस्ताव रखा, और दहेज की भेंट रखी। शिमोन और लेवी ने झूठी मित्रता दिखाते हुए नगर के पुरुषों को खतना कराने के लिए राजी कर लिया, परन्तु उनके स्वस्थ होने से पहले उन पर हमला कर दिया और अपनी बहन के अपमान का बदला लेने के लिए उन्हें मार डाला।</p><p>“हमोर” वह इब्रानी शब्द है जिसका उपयोग याकूब अपने पुत्रों को आशीष देते समय इस्साकार के लिए करता है (<a href=\"https://ref.ly/Gen49:14\">उत 49:14</a>) और यह पुराने नियम में &quot;<span>गदाह</span>&quot; के लिए सामान्य शब्द है (उदाहरण के लिए, <a href=\"https://ref.ly/Gen42:26\">उत 42:26</a>; <a href=\"https://ref.ly/Exod20:17\">निर्ग 20:17</a>; <a href=\"https://ref.ly/Judg15:15\">न्यायि 15:15</a>; <a href=\"https://ref.ly/Isa1:3\">यशा 1:3</a>; <a href=\"https://ref.ly/Zech9:9\">जक 9:9</a>)।</p>",
    "associations": {
      "passage": [
        {
          "start_ref": "01034002",
          "start_ref_usfm": "GEN 34:2",
          "end_ref": "01034002",
          "end_ref_usfm": "GEN 34:2"
        },
        {
          "start_ref": "01042026",
          "start_ref_usfm": "GEN 42:26",
          "end_ref": "01042026",
          "end_ref_usfm": "GEN 42:26"
        },
        {
          "start_ref": "01049014",
          "start_ref_usfm": "GEN 49:14",
          "end_ref": "01049014",
          "end_ref_usfm": "GEN 49:14"
        },
        {
          "start_ref": "02020017",
          "start_ref_usfm": "EXO 20:17",
          "end_ref": "02020017",
          "end_ref_usfm": "EXO 20:17"
        },
        {
          "start_ref": "07015015",
          "start_ref_usfm": "JDG 15:15",
          "end_ref": "07015015",
          "end_ref_usfm": "JDG 15:15"
        },
        {
          "start_ref": "23001003",
          "start_ref_usfm": "ISA 1:3",
          "end_ref": "23001003",
          "end_ref_usfm": "ISA 1:3"
        },
        {
          "start_ref": "38009009",
          "start_ref_usfm": "ZEC 9:9",
          "end_ref": "38009009",
          "end_ref_usfm": "ZEC 9:9"
        }
      ],
      "resource": []
    }
  }
]