[
  {
    "content_id": 4117,
    "reference_id": 3285,
    "title": "Beno",
    "media_type": "Text",
    "index_reference": "beno",
    "language": "eng",
    "content": "<h1>BENO</h1><p>Jaaziah’s son who is listed as one of the Levites assigned to temple duty (<a href=\"https://ref.ly/1Chr24:26-1Chr24:27\">1&nbsp;Chronicles 24:26</a><a href=\"https://ref.ly/1Chr24:26-1Chr24:27\">–</a><a href=\"https://ref.ly/1Chr24:26-1Chr24:27\">27</a>). It is possible that the Hebrew word is not a proper name, so, it has sometimes been translated “his son.”</p>",
    "associations": {
      "passage": [
        {
          "start_ref": "13024026",
          "start_ref_usfm": "1CH 24:26",
          "end_ref": "13024027",
          "end_ref_usfm": "1CH 24:27"
        }
      ],
      "resource": []
    }
  }
]