[
  {
    "content_id": 5655,
    "reference_id": 4823,
    "title": "Hapharaim",
    "media_type": "Text",
    "index_reference": "hapharaim",
    "language": "eng",
    "content": "<h1>HAPHARAIM</h1><p>Town included in the territory allotted to Issachar’s tribe for an inheritance (<a href=\"https://ref.ly/Josh19:19\">Jos 19:19</a>). Some scholars have identified it with et-Taiyibeh, about ten miles (16 kilometers) northwest of Beth-shan.</p>",
    "associations": {
      "passage": [
        {
          "start_ref": "06019019",
          "start_ref_usfm": "JOS 19:19",
          "end_ref": "06019019",
          "end_ref_usfm": "JOS 19:19"
        }
      ],
      "resource": []
    }
  }
]