[
  {
    "content_id": 5761,
    "reference_id": 4929,
    "title": "Hebron (Person)",
    "media_type": "Text",
    "index_reference": "hebron (person)",
    "language": "eng",
    "content": "<h1>HEBRON (Person)</h1><ol><li><p>The third of Kohath’s four sons. Hebron was a descendant of Levi (<a href=\"https://ref.ly/Exod6:18\">Exodus 6:18</a>; <a href=\"https://ref.ly/Num3:19\">Numbers 3:19</a>; <a href=\"https://ref.ly/1Chr6:2,1Chr6:18\">1&nbsp;Chronicles 6:2, 18</a>; <a href=\"https://ref.ly/1Chr23:12\">23:12</a>). Hebron’s sons were Jeriah, Amariah, Jahaziel, and Jekameam (<a href=\"https://ref.ly/1Chr23:19\">1&nbsp;Chronicles 23:19</a>). Hebron’s descendants were called the Hebronites. They are mentioned in a census taken in the plains of Moab (<a href=\"https://ref.ly/Num26:58\">Numbers 26:58</a>). The Hebronites are mentioned in connection with the transfer of the ark to Jerusalem in David’s time (<a href=\"https://ref.ly/1Chr15:9\">1&nbsp;Chronicles 15:9</a>; <a href=\"https://ref.ly/1Chr26:23,1Chr26:30-1Chr26:31\">26:23, 30–31</a>).</p></li><li><p>Mareshah’s son and Korah’s father (<a href=\"https://ref.ly/1Chr2:42-1Chr2:43\">1&nbsp;Chronicles 2:42–43</a>).</p></li></ol>",
    "associations": {
      "passage": [
        {
          "start_ref": "02006018",
          "start_ref_usfm": "EXO 6:18",
          "end_ref": "02006018",
          "end_ref_usfm": "EXO 6:18"
        },
        {
          "start_ref": "04003019",
          "start_ref_usfm": "NUM 3:19",
          "end_ref": "04003019",
          "end_ref_usfm": "NUM 3:19"
        },
        {
          "start_ref": "04026058",
          "start_ref_usfm": "NUM 26:58",
          "end_ref": "04026058",
          "end_ref_usfm": "NUM 26:58"
        },
        {
          "start_ref": "13006002",
          "start_ref_usfm": "1CH 6:2",
          "end_ref": "13006002",
          "end_ref_usfm": "1CH 6:2"
        },
        {
          "start_ref": "13006018",
          "start_ref_usfm": "1CH 6:18",
          "end_ref": "13006018",
          "end_ref_usfm": "1CH 6:18"
        },
        {
          "start_ref": "13015009",
          "start_ref_usfm": "1CH 15:9",
          "end_ref": "13015009",
          "end_ref_usfm": "1CH 15:9"
        },
        {
          "start_ref": "13023012",
          "start_ref_usfm": "1CH 23:12",
          "end_ref": "13023012",
          "end_ref_usfm": "1CH 23:12"
        },
        {
          "start_ref": "13023019",
          "start_ref_usfm": "1CH 23:19",
          "end_ref": "13023019",
          "end_ref_usfm": "1CH 23:19"
        },
        {
          "start_ref": "13026023",
          "start_ref_usfm": "1CH 26:23",
          "end_ref": "13026023",
          "end_ref_usfm": "1CH 26:23"
        },
        {
          "start_ref": "13026030",
          "start_ref_usfm": "1CH 26:30",
          "end_ref": "13026031",
          "end_ref_usfm": "1CH 26:31"
        },
        {
          "start_ref": "13002042",
          "start_ref_usfm": "1CH 2:42",
          "end_ref": "13002043",
          "end_ref_usfm": "1CH 2:43"
        }
      ],
      "resource": []
    }
  }
]