[
  {
    "content_id": 6527,
    "reference_id": 5695,
    "title": "Kebar",
    "media_type": "Text",
    "index_reference": "kebar",
    "language": "eng",
    "content": "<h1>KEBAR</h1><p>Canal in Babylonia. The prophet Ezekiel, who was among the exiles from the southern kingdom of Judah, received visions from God while living in the area of the Kebar Canal (<a href=\"https://ref.ly/Ezek1:1,Ezek1:3\">Ez 1:1, 3</a>; <a href=\"https://ref.ly/Ezek3:15,Ezek3:23\">3:15, 23</a>; <a href=\"https://ref.ly/Ezek10:15,Ezek10:20,Ezek10:22\">10:15, 20, 22</a>; <a href=\"https://ref.ly/Ezek43:3\">43:3</a>). Secular Babylonian texts refer to a <em>nar Kabaru</em> that is believed to be the same canal.</p>",
    "associations": {
      "passage": [
        {
          "start_ref": "26001001",
          "start_ref_usfm": "EZK 1:1",
          "end_ref": "26001001",
          "end_ref_usfm": "EZK 1:1"
        },
        {
          "start_ref": "26001003",
          "start_ref_usfm": "EZK 1:3",
          "end_ref": "26001003",
          "end_ref_usfm": "EZK 1:3"
        },
        {
          "start_ref": "26003015",
          "start_ref_usfm": "EZK 3:15",
          "end_ref": "26003015",
          "end_ref_usfm": "EZK 3:15"
        },
        {
          "start_ref": "26003023",
          "start_ref_usfm": "EZK 3:23",
          "end_ref": "26003023",
          "end_ref_usfm": "EZK 3:23"
        },
        {
          "start_ref": "26010015",
          "start_ref_usfm": "EZK 10:15",
          "end_ref": "26010015",
          "end_ref_usfm": "EZK 10:15"
        },
        {
          "start_ref": "26010020",
          "start_ref_usfm": "EZK 10:20",
          "end_ref": "26010020",
          "end_ref_usfm": "EZK 10:20"
        },
        {
          "start_ref": "26010022",
          "start_ref_usfm": "EZK 10:22",
          "end_ref": "26010022",
          "end_ref_usfm": "EZK 10:22"
        },
        {
          "start_ref": "26043003",
          "start_ref_usfm": "EZK 43:3",
          "end_ref": "26043003",
          "end_ref_usfm": "EZK 43:3"
        }
      ],
      "resource": []
    }
  }
]