[
  {
    "content_id": 6884,
    "reference_id": 6052,
    "title": "Makheloth",
    "media_type": "Text",
    "index_reference": "makheloth",
    "language": "eng",
    "content": "<h1>MAKHELOTH</h1><p>A place where the Israelites camped during their journey from Egypt to Canaan. They stopped here after leaving Haradah and before going to Tahath (<a href=\"https://ref.ly/Num33:25-Num33:26\">Numbers 33:25–26</a>). </p><p><em>See</em> <span data-bnType=\"resourceReference\" data-resourceId=\"8231\" data-resourceType=\"TyndaleBibleDictionary\">Wilderness Wanderings</span>.</p>",
    "associations": {
      "passage": [
        {
          "start_ref": "04033025",
          "start_ref_usfm": "NUM 33:25",
          "end_ref": "04033026",
          "end_ref_usfm": "NUM 33:26"
        }
      ],
      "resource": [
        {
          "reference_id": 8231,
          "content_id": 9063,
          "resource_code": "TyndaleBibleDictionary",
          "label": "Wilderness Wanderings",
          "language": "eng"
        }
      ]
    }
  }
]