[
  {
    "content_id": 7284,
    "reference_id": 6452,
    "title": "Nahamani",
    "media_type": "Text",
    "index_reference": "nahamani",
    "language": "eng",
    "content": "<h1>NAHAMANI</h1><p>One of the leading officials who returned with Zerubbabel to Palestine following the exile (<a href=\"https://ref.ly/Neh7:7\">Neh 7:7</a>). His name is omitted in the parallel list of returning officials in <a href=\"https://ref.ly/Ezra2:2\">Ezra 2:2</a>.</p>",
    "associations": {
      "passage": [
        {
          "start_ref": "15002002",
          "start_ref_usfm": "EZR 2:2",
          "end_ref": "15002002",
          "end_ref_usfm": "EZR 2:2"
        },
        {
          "start_ref": "16007007",
          "start_ref_usfm": "NEH 7:7",
          "end_ref": "16007007",
          "end_ref_usfm": "NEH 7:7"
        }
      ],
      "resource": []
    }
  }
]