[
  {
    "content_id": 8597,
    "reference_id": 7765,
    "title": "Spice, Spicery",
    "media_type": "Text",
    "index_reference": "spice, spicery",
    "language": "eng",
    "content": "<h1>SPICE, SPICERY*</h1><p><em>See</em> <span data-bnType=\"resourceReference\" data-resourceId=\"5185\" data-resourceType=\"TyndaleBibleDictionary\">Incense</span>; <span data-bnType=\"resourceReference\" data-resourceId=\"6834\" data-resourceType=\"TyndaleBibleDictionary\">Perfume</span>.</p>",
    "associations": {
      "passage": [],
      "resource": [
        {
          "reference_id": 5185,
          "content_id": 6017,
          "resource_code": "TyndaleBibleDictionary",
          "label": "Incense",
          "language": "eng"
        },
        {
          "reference_id": 6834,
          "content_id": 7666,
          "resource_code": "TyndaleBibleDictionary",
          "label": "Perfume",
          "language": "eng"
        }
      ]
    }
  }
]